unKR/__init__.py
unKR/data/DataPreprocess.py
unKR/data/KGDataModule.py
unKR/data/Sampler.py
unKR/data/__init__.py
unKR/data/base_data_module.py
unKR/eval_task/__init__.py
unKR/eval_task/confidence_prediction.py
unKR/eval_task/link_prediction.py
unKR/eval_task/nDCG.py
unKR/lit_model/BEUrRELitModel.py
unKR/lit_model/BaseLitModel.py
unKR/lit_model/FocusELitModel.py
unKR/lit_model/GMUCLitModel.py
unKR/lit_model/GTransELitModel.py
unKR/lit_model/PASSLEAFLitModel.py
unKR/lit_model/UKGELitModel.py
unKR/lit_model/UKGEPSLLitModel.py
unKR/lit_model/UKGsELitModel.py
unKR/lit_model/UPGATLitModel.py
unKR/lit_model/__init__.py
unKR/lit_model/ssCDLLit.py
unKR/loss/Adv_Loss.py
unKR/loss/BEUrRE_Loss.py
unKR/loss/FocusE_Loss.py
unKR/loss/GMUC_Loss.py
unKR/loss/GMUCp_Loss.py
unKR/loss/GTransE_Loss.py
unKR/loss/Margin_Loss.py
unKR/loss/PASSLEAF_Loss.py
unKR/loss/UKGE_Loss.py
unKR/loss/UKGE_PSL_Loss.py
unKR/loss/UKGsE_Loss.py
unKR/loss/UPGAT_Loss.py
unKR/loss/__init__.py
unKR/loss/ssCDL_loss.py
unKR/model/__init__.py
unKR/model/FSUKGModel/GMUC.py
unKR/model/FSUKGModel/GMUCp.py
unKR/model/FSUKGModel/__init__.py
unKR/model/UKGModel/BEUrRE.py
unKR/model/UKGModel/FocusE.py
unKR/model/UKGModel/GTransE.py
unKR/model/UKGModel/PASSLEAF.py
unKR/model/UKGModel/SSCDL.py
unKR/model/UKGModel/UKGE.py
unKR/model/UKGModel/UKGE_PSL.py
unKR/model/UKGModel/UKGsE.py
unKR/model/UKGModel/UPGAT.py
unKR/model/UKGModel/__init__.py
unKR/model/UKGModel/model.py
unKR/utils/__init__.py
unKR/utils/setup_parser.py
unKR/utils/tools.py
unkr-1.0.3.dist-info/LICENSE
unkr-1.0.3.dist-info/METADATA
unkr-1.0.3.dist-info/WHEEL
unkr-1.0.3.dist-info/top_level.txt
unkr-1.0.3.dist-info/RECORD
