Metadata-Version: 2.1
Name: unkr
Version: 1.0.3
Summary: An Open Source Library for uncertain Knowledge Reasoning
Home-page: https://github.com/CodeSlogan/unKR
Author: SEUKGE
Author-email: slchen@seu.edu.cn
License: UNKNOWN
Platform: UNKNOWN
Classifier: Programming Language :: Python :: 3
Classifier: License :: OSI Approved :: MIT License
Classifier: Operating System :: OS Independent
Requires-Python: >=3.6
Requires-Dist: pytorch-lightning (==1.5.10)
Requires-Dist: PyYAML
Requires-Dist: wandb
Requires-Dist: IPython
Requires-Dist: gensim
